duplicates/__init__.py
duplicates/__main__.py
duplicates/dupfinder.py
duplicates-0.1.0.dist-info/LICENSE
duplicates-0.1.0.dist-info/METADATA
duplicates-0.1.0.dist-info/WHEEL
duplicates-0.1.0.dist-info/entry_points.txt
duplicates-0.1.0.dist-info/top_level.txt
duplicates-0.1.0.dist-info/RECORD
