Metadata-Version: 2.1
Name: duplicates
Version: 0.1.0
Summary: Find identical files in subdirectories
Home-page: https://github.com/sniner/duplicates
Author: Stefan Schönberger
Author-email: me@s5s9r.de
License: UNKNOWN
Platform: any
Classifier: Programming Language :: Python :: 3
Classifier: License :: OSI Approved :: BSD License
Classifier: Operating System :: POSIX
Requires-Python: >=3.6
Provides-Extra: dev
